{
    "TranslationProperties":  {
                                  "Name":  "server.items.Weapon_Longsword_Praetorian_NPC.name"
                              },
    "Parent":  "Weapon_Longsword_Praetorian",
    "PlayerAnimationsId":  "Sword",
    "Utility":  {
                    "Compatible":  true
                },
    "Quality":  "Developer",
    "Tags":  {
                 "Type":  [
                              "Weapon"
                          ],
                 "Family":  [
                                "Longsword"
                            ]
             },
    "Recipe":  {
                   "TimeSeconds":  4,
                   "KnowledgeRequired":  false,
                   "Input":  [
                                 {
                                     "ItemId":  "Ingredient_Bar_Mithril",
                                     "Quantity":  6
                                 },
                                 {
                                     "ItemId":  "Ingredient_Fabric_Scrap_Linen",
                                     "Quantity":  3
                                 },
                                 {
                                     "ItemId":  "Ingredient_Leather_Medium",
                                     "Quantity":  4
                                 }
                             ],
                   "BenchRequirement":  [
                                            {
                                                "Type":  "Crafting",
                                                "Categories":  [
                                                                   "Weapon_Longsword"
                                                               ],
                                                "Id":  "Weapon_Bench",
                                                "RequiredTierLevel":  2
                                            }
                                        ]
               }
}
